<Model id="29c9b718-8915-46ee-a468-26acf3a7bd63" name="人工流产术后健康教育处方" description="适用于重庆大学城附属医院" text="人工流产术后健康教育处方" nodetype="Model" canprint="True" printInOddPages="False" display="11```0`1" Version="1.0.0.229" titledisplay="1`1`1" hospitalcoderange="10027" catalogcode="B+30" illnesstypecode="FFFF" scalemodelxml="" modellogiccontent="" indentEnabled="False" isReview="False" NodeLogicContent="" isform="False" formclass="" maxrefid="11" RelateInstanceId="0">
  <Ref id="11">
    <node identity="0" isfixed="False" spaceholder="0" atomvisibleenabled="False" atomvisible="" diagnosistype="-1" illnesstypecode="" hospitalcoderange="" id="af93e224-ab45-43e6-b95c-c1b5d28df79e" nodetype="Embeded" nodelogiccontent="" name="医师签名（单个医师签名）" text="医师签名（单个医师签名）" description="病史记录者签名" display="11```0`1">
      <node embededId="0" id="395af5e6-1851-4acb-8bf7-05b73aa7ffc2" nodetype="Object" nodelogiccontent="" name="医师签名（单个医师签名）" text="医师签名（单个医师签名）" display="11```0`1">
        <node id="240d0ef4-ba27-4c11-b735-7d62c1f744c3" nodetype="AtomNode" nodelogiccontent="" name="医师签名" text="医师签名" description="院内职工表。" atomtype="String" value="``" ischoiceatom="True" ChoiceType="ShowList" sqlstr="职工表///EmployeeBook///记录状态//1" inputdirect="False" display="1110111````　```0" embededId="7" autoeditnext="True" spaceholder="0" forbidDel="False" />
      </node>
    </node>
  </Ref>
  <node id="da9f1e3d-87b3-4b29-b006-d39cc3e0f7a7" nodetype="DynamicMoleNode" nodelogiccontent="" name="同意书与委托书(同意书内容)" signid="手术中可能出现的意外及风险|419" text="同意书与委托书(同意书内容)" description="各类用药、检查、手术等同意书的内容。" otherid="C-1192" display="11```0`1" permitobjs="" defaultobjs="" allowUserDefine="False" canNotInputText="False" canNull="True" canNullSubmit="True" permittedDoctorGradeRange="" useDiagContinuedPrint="False" nodePrintArea="None" indentLength="0">
    <node text="术后注意事項：&#xA;&#xA;   一、" rtf="\b \'ca\'f5\'ba\'f3\'d7\'a2\'d2\'e2\'ca\'c2\'ed\'97\'a3\'ba\par&#xD;&#xA;\b0\par&#xD;&#xA;\pard    \'d2\'bb\'a1\'a2" nodetype="Text" />
    <node text="适当休息1-2周,避免劳累、着凉,避免长时间卧床。&#xA;&#xA;   二、术后饮食清淡,忌大补。&#xA;&#xA;" rtf="\'ca\'ca\'b5\'b1\'d0\'dd\'cf\'a21-2\'d6\'dc,\'b1\'dc\'c3\'e2\'c0\'cd\'c0\'db\'a1\'a2\'d7\'c5\'c1\'b9,\'b1\'dc\'c3\'e2\'b3\'a4\'ca\'b1\'bc\'e4\'ce\'d4\'b4\'b2\'a1\'a3\par&#xD;&#xA;\par&#xD;&#xA;   \'b6\'fe\'a1\'a2\'ca\'f5\'ba\'f3\'d2\'fb\'ca\'b3\'c7\'e5\'b5\'ad,\'bc\'c9\'b4\'f3\'b2\'b9\'a1\'a3\par&#xD;&#xA;\par&#xD;&#xA;" nodetype="Text" />
    <node text="   三、术后1周内禁止性生活、盆浴、游泳" rtf="   \'c8\'fd\'a1\'a2\'ca\'f5\'ba\'f31\'d6\'dc\'c4\'da\'bd\'fb\'d6\'b9\'d0\'d4\'c9\'fa\'bb\'ee\'a1\'a2\'c5\'e8\'d4\'a1\'a1\'a2\'d3\'ce\'d3\'be" nodetype="Text" />
    <node text=",防止盆腔感染。&#xA;&#xA;" rtf=",\'b7\'c0\'d6\'b9\'c5\'e8\'c7\'bb\'b8\'d0\'c8\'be\'a1\'a3\par&#xD;&#xA;\par&#xD;&#xA;" nodetype="Text" />
    <node text="   四、木后1周返院复査,术后1月月经干浄后返院复査。术后1、3、6、12月我们会电话随访您的月经情況及避孕情況。&#xA;&#xA;   五、人流术后有感染、人流不全、漏吸、宮腔粘连及不孕的可能。因此,发现下列情况请及时来医院检査治疗:&#xA;&#xA;   1.有明显腹痛,阴道出血量多,发烧等异常情況。&#xA;&#xA;" rtf="   \'cb\'c4\'a1\'a2\'c4\'be\'ba\'f31\'d6\'dc\'b7\'b5\'d4\'ba\'b8\'b4\'96\'cb,\'ca\'f5\'ba\'f31\'d4\'c2\'d4\'c2\'be\'ad\'b8\'c9\'9b\'b7\'ba\'f3\'b7\'b5\'d4\'ba\'b8\'b4\'96\'cb\'a1\'a3\'ca\'f5\'ba\'f31\'a1\'a23\'a1\'a26\'a1\'a212\'d4\'c2\'ce\'d2\'c3\'c7\'bb\'e1\'b5\'e7\'bb\'b0\'cb\'e6\'b7\'c3\'c4\'fa\'b5\'c4\'d4\'c2\'be\'ad\'c7\'e9\'9b\'72\'bc\'b0\'b1\'dc\'d4\'d0\'c7\'e9\'9b\'72\'a1\'a3\par&#xD;&#xA;\par&#xD;&#xA;   \'ce\'e5\'a1\'a2\'c8\'cb\'c1\'f7\'ca\'f5\'ba\'f3\'d3\'d0\'b8\'d0\'c8\'be\'a1\'a2\'c8\'cb\'c1\'f7\'b2\'bb\'c8\'ab\'a1\'a2\'c2\'a9\'ce\'fc\'a1\'a2\'8c\'6d\'c7\'bb\'d5\'b3\'c1\'ac\'bc\'b0\'b2\'bb\'d4\'d0\'b5\'c4\'bf\'c9\'c4\'dc\'a1\'a3\'d2\'f2\'b4\'cb,\'b7\'a2\'cf\'d6\'cf\'c2\'c1\'d0\'c7\'e9\'bf\'f6\'c7\'eb\'bc\'b0\'ca\'b1\'c0\'b4\'d2\'bd\'d4\'ba\'bc\'ec\'96\'cb\'d6\'ce\'c1\'c6:\par&#xD;&#xA;\par&#xD;&#xA;   1.\'d3\'d0\'c3\'f7\'cf\'d4\'b8\'b9\'cd\'b4,\'d2\'f5\'b5\'c0\'b3\'f6\'d1\'aa\'c1\'bf\'b6\'e0,\'b7\'a2\'c9\'d5\'b5\'c8\'d2\'ec\'b3\'a3\'c7\'e9\'9b\'72\'a1\'a3\par&#xD;&#xA;\par&#xD;&#xA;" nodetype="Text" />
    <node text="   2.2周内阴道出血不止,出血量多,有血块和烂肉样组织物排出。&#xA;&#xA;" rtf="   2.2\'d6\'dc\'c4\'da\'d2\'f5\'b5\'c0\'b3\'f6\'d1\'aa\'b2\'bb\'d6\'b9,\'b3\'f6\'d1\'aa\'c1\'bf\'b6\'e0,\'d3\'d0\'d1\'aa\'bf\'e9\'ba\'cd\'c0\'c3\'c8\'e2\'d1\'f9\'d7\'e9\'d6\'af\'ce\'ef\'c5\'c5\'b3\'f6\'a1\'a3\par&#xD;&#xA;\par&#xD;&#xA;" nodetype="Text" />
    <node text="   3.早孕反应仍然存在。&#xA;&#xA;   4.伴随月经周期有下腹部疼痛,月经量减少或闭经等。&#xA;&#xA;   六、人流术后最早2周就可恢复排卵 ,若不及吋避孕可能在月径恢隻前再次意外妊娠,因此建议您术后立即采取高效的避孕方式。若有生育要求,建议半年后受孕较为理想。&#xA;&#xA;   七、术后避孕方式相关注意事項:&#xA;&#xA;   1.短效口服避孕药服用方法:药流后当晩开始服用第一片,毎天一片(定时),避免漏药;【 若选择21片剂型(优思明),连续服用21天 ,停药7天后接着服用第二盒】:【若选择28片剂型(优思悦),连续服用无需停药】。&#xA;&#xA;   2.安装宮内节育器 (IUD/1US):转经后采用,见安环术后教育处方" rtf="   3.\'d4\'e7\'d4\'d0\'b7\'b4\'d3\'a6\'c8\'d4\'c8\'bb\'b4\'e6\'d4\'da\'a1\'a3\par&#xD;&#xA;\par&#xD;&#xA;   4.\'b0\'e9\'cb\'e6\'d4\'c2\'be\'ad\'d6\'dc\'c6\'da\'d3\'d0\'cf\'c2\'b8\'b9\'b2\'bf\'cc\'db\'cd\'b4,\'d4\'c2\'be\'ad\'c1\'bf\'bc\'f5\'c9\'d9\'bb\'f2\'b1\'d5\'be\'ad\'b5\'c8\'a1\'a3\par&#xD;&#xA;\par&#xD;&#xA;   \'c1\'f9\'a1\'a2\'c8\'cb\'c1\'f7\'ca\'f5\'ba\'f3\'d7\'ee\'d4\'e72\'d6\'dc\'be\'cd\'bf\'c9\'bb\'d6\'b8\'b4\'c5\'c5\'c2\'d1 ,\'c8\'f4\'b2\'bb\'bc\'b0\'85\'bc\'b1\'dc\'d4\'d0\'bf\'c9\'c4\'dc\'d4\'da\'d4\'c2\'be\'b6\'bb\'d6\'eb\'62\'c7\'b0\'d4\'d9\'b4\'ce\'d2\'e2\'cd\'e2\'c8\'d1\'c9\'ef,\'d2\'f2\'b4\'cb\'bd\'a8\'d2\'e9\'c4\'fa\'ca\'f5\'ba\'f3\'c1\'a2\'bc\'b4\'b2\'c9\'c8\'a1\'b8\'df\'d0\'a7\'b5\'c4\'b1\'dc\'d4\'d0\'b7\'bd\'ca\'bd\'a1\'a3\'c8\'f4\'d3\'d0\'c9\'fa\'d3\'fd\'d2\'aa\'c7\'f3,\'bd\'a8\'d2\'e9\'b0\'eb\'c4\'ea\'ba\'f3\'ca\'dc\'d4\'d0\'bd\'cf\'ce\'aa\'c0\'ed\'cf\'eb\'a1\'a3\par&#xD;&#xA;\par&#xD;&#xA;   \'c6\'df\'a1\'a2\'ca\'f5\'ba\'f3\'b1\'dc\'d4\'d0\'b7\'bd\'ca\'bd\'cf\'e0\'b9\'d8\'d7\'a2\'d2\'e2\'ca\'c2\'ed\'97:\par&#xD;&#xA;\par&#xD;&#xA;   1.\'b6\'cc\'d0\'a7\'bf\'da\'b7\'fe\'b1\'dc\'d4\'d0\'d2\'a9\'b7\'fe\'d3\'c3\'b7\'bd\'b7\'a8:\'d2\'a9\'c1\'f7\'ba\'f3\'b5\'b1\'95\'8a\'bf\'aa\'ca\'bc\'b7\'fe\'d3\'c3\'b5\'da\'d2\'bb\'c6\'ac,\'9a\'b0\'cc\'ec\'d2\'bb\'c6\'ac(\'b6\'a8\'ca\'b1),\'b1\'dc\'c3\'e2\'c2\'a9\'d2\'a9;\'a1\'be \'c8\'f4\'d1\'a1\'d4\'f121\'c6\'ac\'bc\'c1\'d0\'cd(\'d3\'c5\'cb\'bc\'c3\'f7),\'c1\'ac\'d0\'f8\'b7\'fe\'d3\'c321\'cc\'ec ,\'cd\'a3\'d2\'a97\'cc\'ec\'ba\'f3\'bd\'d3\'d7\'c5\'b7\'fe\'d3\'c3\'b5\'da\'b6\'fe\'ba\'d0\'a1\'bf:\'a1\'be\'c8\'f4\'d1\'a1\'d4\'f128\'c6\'ac\'bc\'c1\'d0\'cd(\'d3\'c5\'cb\'bc\'d4\'c3),\'c1\'ac\'d0\'f8\'b7\'fe\'d3\'c3\'ce\'de\'d0\'e8\'cd\'a3\'d2\'a9\'a1\'bf\'a1\'a3\par&#xD;&#xA;\par&#xD;&#xA;\pard    2.\'b0\'b2\'d7\'b0\'8c\'6d\'c4\'da\'bd\'da\'d3\'fd\'c6\'f7 (IUD/1US):\'d7\'aa\'be\'ad\'ba\'f3\'b2\'c9\'d3\'c3,\'bc\'fb\'b0\'b2\'bb\'b7\'ca\'f5\'ba\'f3\'bd\'cc\'d3\'fd\'b4\'a6\'b7\'bd" nodetype="Text" />
    <node text="&#xA;&#xA;&#xA;&#xA;&#xA;&#xA;医师(签字 /章 ): " rtf="\par&#xD;&#xA;\par&#xD;&#xA;\par&#xD;&#xA;\par&#xD;&#xA;\par&#xD;&#xA;\par&#xD;&#xA;\pard\'d2\'bd\'ca\'a6(\'c7\'a9\'d7\'d6 /\'d5\'c2 ): " nodetype="Text" />
    <node refid="11" nodetype="Embeded" />
    <node text="    " rtf="    " nodetype="Text" />
    <node text="  " rtf="\b   " nodetype="Text" />
    <node text="    " rtf="    " nodetype="Text" />
    <node text="                       " rtf="\b                        " nodetype="Text" />
    <node text="    咨询电话:65714731" rtf="    \'d7\'c9\'d1\'af\'b5\'e7\'bb\'b0:65714731" nodetype="Text" />
    <node text="&#xA;" rtf="\par&#xD;&#xA;" nodetype="Text" />
  </node>
</Model>